{
  "urls": [
    {
      "title": "BCG Revaccination for the Prevention of Mycobacterium tuberculosis Infection - PubMed",
      "content": "BCG Revaccination for the Prevention of Mycobacterium tuberculosis Infection\n- PMID: 40334156\n- DOI: 10.1056/NEJMoa2412381\nBCG Revaccination for the Prevention of Mycobacterium tuberculosis Infection\nAbstract\nBackground: In a previous phase 2 trial, bacille Calmette-Gu\u00e9rin (BCG) revaccination was not shown to provide protection from primary Mycobacterium tuberculosis infection but prevented sustained M. tuberculosis infection, defined by an initial conversion on a QuantiFERON-TB (QFT) test (an interferon-\u03b3 release assay) from negative to positive, followed by two additional positive QFT tests at 3 and 6 months after the initial conversion (a secondary end point). A vaccine efficacy of 45% (95% confidence interval [CI], 6 to 68) was observed.\nMethods: We performed a phase 2b, double-blind, randomized, placebo-controlled trial to evaluate the efficacy of BCG revaccination, as compared with placebo, for the prevention of sustained QFT test conversion (primary end point) in QFT test-negative, human immunodeficiency virus (HIV)-negative adolescents. Adverse events were assessed in a secondary analysis, and immunogenicity was assessed in an exploratory analysis. Vaccine efficacy was evaluated in the modified intention-to-treat population, which included all the participants who had undergone randomization, received the BCG vaccine or placebo, and had a negative QFT test 10 weeks after receipt of BCG vaccine or placebo; the last criterion was added to exclude participants with M. tuberculosis infection around the time that the vaccine or placebo was administered. Hazard ratios and 95% confidence intervals were estimated from a stratified Cox proportional-hazards model.\nResults: A total of 1836 participants underwent randomization; 918 received the BCG vaccine, and 917 received placebo. After a median 30 months of follow-up, a sustained QFT test conversion was observed in 62 of 871 participants in the BCG-vaccine group and 59 of 849 participants in the placebo group. The hazard ratio for a sustained QFT test conversion (BCG vaccine vs. placebo) was 1.04 (95% CI, 0.73 to 1.48), for a vaccine efficacy point estimate of -3.8% (95% CI, -48.3 to 27.4). Adverse events occurred more frequently in the BCG-vaccine group than in the placebo group, and most were due to injection-site reactions (pain, redness, swelling, and ulceration). BCG revaccination induced cytokine-positive type 1 helper CD4 T cells.\nConclusions: BCG revaccination in QFT-test negative, HIV-negative adolescents did not provide protection from sustained M. tuberculosis infection. (Funded by the Gates Foundation; ClinicalTrials.gov number NCT04152161.).\nCopyright \u00a9 2025 Massachusetts Medical Society.\nPublication types\nMeSH terms\nSubstances\nAssociated data\nLinkOut - more resources\nFull Text Sources\nResearch Materials",
      "beautifulsoup_metadata": {
        "HandheldFriendly": "True",
        "MobileOptimized": "320",
        "viewport": "width=device-width, initial-scale=1.0",
        "ncbi_sg_optimize_id": "",
        "theme-color": "#20558a",
        "referrer": "origin-when-cross-origin",
        "ncbi_pinger_gtm_track": "true",
        "ncbi_app": "pubmed",
        "ncbi_db": "pubmed",
        "ncbi_phid": "819400011DD8728500002C1631D5C4D4.1.m_5",
        "ncbi_pinger_stat_url": "https://pubmed.ncbi.nlm.nih.gov/stat",
        "log_category": "literature",
        "ncbi_cost_center": "pubmed",
        "ncbi_pdid": "abstract",
        "log_op": "retrieve",
        "uid": "40334156",
        "ncbi_uid": "40334156",
        "log_displayeduids": "40334156",
        "log_source_db": "pubmed",
        "log_icons_present": "true",
        "description": "BCG revaccination in QFT-test negative, HIV-negative adolescents did not provide protection from sustained <i>M. tuberculosis</i> infection. (Funded by the Gates Foundation; ClinicalTrials.gov number NCT04152161.).",
        "keywords": "pmid:40334156, doi:10.1056/NEJMoa2412381, Randomized Controlled Trial, Clinical Trial, Phase II, Multicenter Study, Alexander C Schmidt, Lee Fairlie, CollabAuthor(name='BCG REVAX Study Team', investigators=[Author(firstnames='Chrisna', lastname='Andersen', initials='C', affs=[], is_editor=False, suffix=None, equal_contrib=False), Author(firstnames='Mia van', lastname='Velden', initials='MV', affs=[], is_editor=False, suffix=None, equal_contrib=False), Author(firstnames='Jeanne-Marie', lastname='Myburgh', initials='JM', affs=[], is_editor=False, suffix=None, equal_contrib=False), Author(firstnames='Debra', lastname='Pote', initials='D', affs=[], is_editor=False, suffix=None, equal_contrib=False), Author(firstnames='Erica', lastname='Bailey', initials='E', affs=[], is_editor=False, suffix=None, equal_contrib=False), Author(firstnames='W A', lastname='Koegelenberg', initials='WA', affs=[], is_editor=False, suffix=None, equal_contrib=False), Author(firstnames='Candise', lastname='Hans', initials='C', affs=[], is_editor=False, suffix=None, equal_contrib=False), Author(firstnames='Eileen', lastname='Fortuin', initials='E', affs=[], is_editor=False, suffix=None, equal_contrib=False), Author(firstnames='Thandolwethu', lastname='Dada', initials='T', affs=[], is_editor=False, suffix=None, equal_contrib=False), Author(firstnames='Zeti', lastname='Telite', initials='Z', affs=[], is_editor=False, suffix=None, equal_contrib=False), Author(firstnames='Mziwoxolo', lastname='Nqwede', initials='M', affs=[], is_editor=False, suffix=None, equal_contrib=False), Author(firstnames='Adri', lastname='Holm', initials='A', affs=[], is_editor=False, suffix=None, equal_contrib=False), Author(firstnames='Nomthandazo', lastname='Matolengwe', initials='N', affs=[], is_editor=False, suffix=None, equal_contrib=False), Author(firstnames='Noxolo', lastname='Bonakele', initials='N', affs=[], is_editor=False, suffix=None, equal_contrib=False), Author(firstnames='Anine', lastname='Theron', initials='A', affs=[], is_editor=False, suffix=None, equal_contrib=False), Author(firstnames='Babalwa', lastname='Khaya', initials='B', affs=[], is_editor=False, suffix=None, equal_contrib=False), Author(firstnames='Bonita', lastname='Smitsdorff', initials='B', affs=[], is_editor=False, suffix=None, equal_contrib=False), Author(firstnames='Bukiwe', lastname='Mnqebisa', initials='B', affs=[], is_editor=False, suffix=None, equal_contrib=False), Author(firstnames='Caro-Lee', lastname='Saal', initials='CL', affs=[], is_editor=False, suffix=None, equal_contrib=False), Author(firstnames='Cleon', lastname='Ncayiya', initials='C', affs=[], is_editor=False, suffix=None, equal_contrib=False), Author(firstnames='Edith', lastname='Kiribikiri', initials='E', affs=[], is_editor=False, suffix=None, equal_contrib=False), Author(firstnames='Elaine', lastname='Sebastian', initials='E', affs=[], is_editor=False, suffix=None, equal_contrib=False), Author(firstnames='Ferial', lastname='Mahed', initials='F', affs=[], is_editor=False, suffix=None, equal_contrib=False), Author(firstnames='Hlengiwe', lastname='Mkhize', initials='H', affs=[], is_editor=False, suffix=None, equal_contrib=False), Author(firstnames='Jenipher', lastname='Gelant', initials='J', affs=[], is_editor=False, suffix=None, equal_contrib=False), Author(firstnames='Julio', lastname='Muller', initials='J', affs=[], is_editor=False, suffix=None, equal_contrib=False), Author(firstnames='Justine', lastname='Stewart', initials='J', affs=[], is_editor=False, suffix=None, equal_contrib=False), Author(firstnames='Kgomotso', lastname='Mocumi', initials='K', affs=[], is_editor=False, suffix=None, equal_contrib=False), Author(firstnames='Khadija', lastname='Gool', initials='K', affs=[], is_editor=False, suffix=None, equal_contrib=False), Author(firstnames='Lindsay', lastname='Jeffrey', initials='L', affs=[], is_editor=False, suffix=None, equal_contrib=False), Author(firstnames='Litha', lastname='Gogo', initials='L', affs=[], is_editor=False, suffix=None, equal_contrib=False), Author(firstnames='Llewellyn', lastname='Fleurs', initials='L', affs=[], is_editor=False, suffix=None, equal_contrib=False), Author(firstnames='Lulama', lastname='Maqungo', initials='L', affs=[], is_editor=False, suffix=None, equal_contrib=False), Author(firstnames='Lulu', lastname='Nair', initials='L', affs=[], is_editor=False, suffix=None, equal_contrib=False), Author(firstnames='Michaela', lastname='Kingwill', initials='M', affs=[], is_editor=False, suffix=None, equal_contrib=False), Author(firstnames='Michelle', lastname='Van Der Merve', initials='M', affs=[], is_editor=False, suffix=None, equal_contrib=False), Author(firstnames='Mluleki', lastname='Nompondwana', initials='M', affs=[], is_editor=False, suffix=None, equal_contrib=False), Author(firstnames='Mustafaa', lastname='Maarman', initials='M', affs=[], is_editor=False, suffix=None, equal_contrib=False), Author(firstnames='Mzamo', lastname='Ntanjana', initials='M', affs=[], is_editor=False, suffix=None, equal_contrib=False), Author(firstnames='Ndiseka', lastname='Nashwa', initials='N', affs=[], is_editor=False, suffix=None, equal_contrib=False), Author(firstnames='Njabulo', lastname='Shangase', initials='N', affs=[], is_editor=False, suffix=None, equal_contrib=False), Author(firstnames='Nobubele', lastname='Mshudulu', initials='N', affs=[], is_editor=False, suffix=None, equal_contrib=False), Author(firstnames='Nocwaka', lastname='Magobiane', initials='N', affs=[], is_editor=False, suffix=None, equal_contrib=False), Author(firstnames='Nokwayintombi', lastname='Scotch', initials='N', affs=[], is_editor=False, suffix=None, equal_contrib=False), Author(firstnames='Noluxolo', lastname='Mgxekeza', initials='N', affs=[], is_editor=False, suffix=None, equal_contrib=False), Author(firstnames='Nombeko', lastname='Mpongo', initials='N', affs=[], is_editor=False, suffix=None, equal_contrib=False), Author(firstnames='Nombongo', lastname='Mayekiso', initials='N', affs=[], is_editor=False, suffix=None, equal_contrib=False), Author(firstnames='Nontshukumo', lastname='Ngqabe', initials='N', affs=[], is_editor=False, suffix=None, equal_contrib=False), Author(firstnames='Noxolo', lastname='Mona', initials='N', affs=[], is_editor=False, suffix=None, equal_contrib=False), Author(firstnames='Nozicelo', lastname='Mbiza', initials='N', affs=[], is_editor=False, suffix=None, equal_contrib=False), Author(firstnames='Ntombekhaya', lastname='Zoneleni', initials='N', affs=[], is_editor=False, suffix=None, equal_contrib=False), Author(firstnames='Nwabisa', lastname='Danster', initials='N', affs=[], is_editor=False, suffix=None, equal_contrib=False), Author(firstnames='Pam', lastname='Makhamba', initials='P', affs=[], is_editor=False, suffix=None, equal_contrib=False), Author(firstnames='Pamela', lastname='Dukwe', initials='P', affs=[], is_editor=False, suffix=None, equal_contrib=False), Author(firstnames='Priscilla', lastname='Mvinjelwa', initials='P', affs=[], is_editor=False, suffix=None, equal_contrib=False), Author(firstnames='Ridley', lastname='Howard', initials='R', affs=[], is_editor=False, suffix=None, equal_contrib=False), Author(firstnames='Samantha', lastname='Geduld', initials='S', affs=[], is_editor=False, suffix=None, equal_contrib=False), Author(firstnames='Sibusiso', lastname='Gumede', initials='S', affs=[], is_editor=False, suffix=None, equal_contrib=False), Author(firstnames='Sihle', lastname='Dyanti', initials='S', affs=[], is_editor=False, suffix=None, equal_contrib=False), Author(firstnames='Tamara', lastname='Honono', initials='T', affs=[], is_editor=False, suffix=None, equal_contrib=False), Author(firstnames='Thandokazi', lastname='Tofile', initials='T', affs=[], is_editor=False, suffix=None, equal_contrib=False), Author(firstnames='Thembakazi', lastname='Daki', initials='T', affs=[], is_editor=False, suffix=None, equal_contrib=False), Author(firstnames='Thembisile', lastname='Yola', initials='T', affs=[], is_editor=False, suffix=None, equal_contrib=False), Author(firstnames='Thobeka', lastname='Coba', initials='T', affs=[], is_editor=False, suffix=None, equal_contrib=False), Author(firstnames='Valerie', lastname='Mlotshwa', initials='V', affs=[], is_editor=False, suffix=None, equal_contrib=False), Author(firstnames='Winnifred', lastname='Gumula', initials='W', affs=[], is_editor=False, suffix=None, equal_contrib=False), Author(firstnames='Xolani', lastname='Gxako', initials='X', affs=[], is_editor=False, suffix=None, equal_contrib=False), Author(firstnames='Zandile', lastname='Mkhize', initials='Z', affs=[], is_editor=False, suffix=None, equal_contrib=False), Author(firstnames='Jabulisile', lastname='Zuma', initials='J', affs=[], is_editor=False, suffix=None, equal_contrib=False), Author(firstnames='Nomvuselelo', lastname='Tshongoyi', initials='N', affs=[], is_editor=False, suffix=None, equal_contrib=False), Author(firstnames='Ebrahim', lastname='Jacobs', initials='E', affs=[], is_editor=False, suffix=None, equal_contrib=False), Author(firstnames='Abigail', lastname='van der Linde', initials='A', affs=[], is_editor=False, suffix=None, equal_contrib=False), Author(firstnames='Baphiwe', lastname='Tose', initials='B', affs=[], is_editor=False, suffix=None, equal_contrib=False), Author(firstnames='Noluthano', lastname='Khiya', initials='N', affs=[], is_editor=False, suffix=None, equal_contrib=False), Author(firstnames='Amina', lastname='Ismail', initials='A', affs=[], is_editor=False, suffix=None, equal_contrib=False), Author(firstnames='Shakeera', lastname='Arnolds', initials='S', affs=[], is_editor=False, suffix=None, equal_contrib=False), Author(firstnames='Sithembiso', lastname='Mbhele', initials='S', affs=[], is_editor=False, suffix=None, equal_contrib=False), Author(firstnames='Junaid', lastname='Rawoot', initials='J', affs=[], is_editor=False, suffix=None, equal_contrib=False), Author(firstnames='Zanoxolo', lastname='Mthethi', initials='Z', affs=[], is_editor=False, suffix=None, equal_contrib=False), Author(firstnames='Jaco', lastname='Horak', initials='J', affs=[], is_editor=False, suffix=None, equal_contrib=False), Author(firstnames='Philippa', lastname='Macdonald', initials='P', affs=[], is_editor=False, suffix=None, equal_contrib=False), Author(firstnames='Scott', lastname='Mahoney', initials='S', affs=[], is_editor=False, suffix=None, equal_contrib=False), Author(firstnames='Lusanda', lastname='Yekani', initials='L', affs=[], is_editor=False, suffix=None, equal_contrib=False), Author(firstnames='Nazmie', lastname='Pearce', initials='N', affs=[], is_editor=False, suffix=None, equal_contrib=False), Author(firstnames='Janice', lastname='Groenewald', initials='J', affs=[], is_editor=False, suffix=None, equal_contrib=False), Author(firstnames='Theodorah', lastname='Rirhandzu Ndzhukule', initials='T', affs=[], is_editor=False, suffix=None, equal_contrib=False), Author(firstnames='Gakiema', lastname='Malan', initials='G', affs=[], is_editor=False, suffix=None, equal_contrib=False), Author(firstnames='Steven', lastname='Innes', initials='S', affs=[], is_editor=False, suffix=None, equal_contrib=False), Author(firstnames='Khaya', lastname='Vakala', initials='K', affs=[], is_editor=False, suffix=None, equal_contrib=False), Author(firstnames='Lungile', lastname='Mafilika', initials='L', affs=[], is_editor=False, suffix=None, equal_contrib=False), Author(firstnames='Yonela', lastname='Mathiso', initials='Y', affs=[], is_editor=False, suffix=None, equal_contrib=False), Author(firstnames='Lindsay', lastname='Jeffery', initials='L', affs=[], is_editor=False, suffix=None, equal_contrib=False), Author(firstnames='Henrich', lastname='Strumper', initials='H', affs=[], is_editor=False, suffix=None, equal_contrib=False), Author(firstnames='Mechia', lastname='Gerber', initials='M', affs=[], is_editor=False, suffix=None, equal_contrib=False), Author(firstnames='Sonia', lastname='Stryers', initials='S', affs=[], is_editor=False, suffix=None, equal_contrib=False), Author(firstnames='Beaulah', lastname='Speckman', initials='B', affs=[], is_editor=False, suffix=None, equal_contrib=False), Author(firstnames='Bongani', lastname='Diamond', initials='B', affs=[], is_editor=False, suffix=None, equal_contrib=False), Author(firstnames='Ilse', lastname='Davids', initials='I', affs=[], is_editor=False, suffix=None, equal_contrib=False), Author(firstnames='Lauren', lastname='Mactavie', initials='L', affs=[], is_editor=False, suffix=None, equal_contrib=False), Author(firstnames='Ruwiyda', lastname='Jansen', initials='R', affs=[], is_editor=False, suffix=None, equal_contrib=False), Author(firstnames='Nambitha', lastname='Nqakala', initials='N', affs=[], is_editor=False, suffix=None, equal_contrib=False), Author(firstnames='Nompumelelo', lastname='Cetwayo', initials='N', affs=[], is_editor=False, suffix=None, equal_contrib=False), Author(firstnames='Xoliswa', lastname='Kelepu', initials='X', affs=[], is_editor=False, suffix=None, equal_contrib=False), Author(firstnames='Roxane', lastname='Herling', initials='R', affs=[], is_editor=False, suffix=None, equal_contrib=False), Author(firstnames='Likhaya', lastname='Sizani', initials='L', affs=[], is_editor=False, suffix=None, equal_contrib=False), Author(firstnames='Julia', lastname='Amsterdam', initials='J', affs=[], is_editor=False, suffix=None, equal_contrib=False), Author(firstnames='Nicolette', lastname='Tredoux', initials='N', affs=[], is_editor=False, suffix=None, equal_contrib=False), Author(firstnames='Marwou', lastname='de Kock', initials='M', affs=[], is_editor=False, suffix=None, equal_contrib=False), Author(firstnames='Michelle', lastname='Williams', initials='M', affs=[], is_editor=False, suffix=None, equal_contrib=False), Author(firstnames='Claire', lastname='Imbratta', initials='C', affs=[], is_editor=False, suffix=None, equal_contrib=False), Author(firstnames='Lungisa', lastname='Jaxa', initials='L', affs=[], is_editor=False, suffix=None, equal_contrib=False), Author(firstnames='Lauren', lastname='Cruywagen', initials='L', affs=[], is_editor=False, suffix=None, equal_contrib=False), Author(firstnames='Constance', lastname='Schreuder', initials='C', affs=[], is_editor=False, suffix=None, equal_contrib=False), Author(firstnames='Munyaradzi', lastname='Musvosvi', initials='M', affs=[], is_editor=False, suffix=None, equal_contrib=False), Author(firstnames='Nicole', lastname='Bilek', initials='N', affs=[], is_editor=False, suffix=None, equal_contrib=False), Author(firstnames='Yolundi', lastname='Cloete', initials='Y', affs=[], is_editor=False, suffix=None, equal_contrib=False), Author(firstnames='Mzwandile', lastname='Erasmus', initials='M', affs=[], is_editor=False, suffix=None, equal_contrib=False), Author(firstnames='Onke', lastname='Nombida', initials='O', affs=[], is_editor=False, suffix=None, equal_contrib=False), Author(firstnames='Hadn', lastname='Africa', initials='H', affs=[], is_editor=False, suffix=None, equal_contrib=False), Author(firstnames='Marcia', lastname='Steyn', initials='M', affs=[], is_editor=False, suffix=None, equal_contrib=False), Author(firstnames='Habibullah', lastname='Valley', initials='H', affs=[], is_editor=False, suffix=None, equal_contrib=False), Author(firstnames='Sandisiwe', lastname='Mangali', initials='S', affs=[], is_editor=False, suffix=None, equal_contrib=False), Author(firstnames='Hlengiwe', lastname='Nkambule', initials='H', affs=[], is_editor=False, suffix=None, equal_contrib=False), Author(firstnames='Lebohang', lastname='Makhethe', initials='L', affs=[], is_editor=False, suffix=None, equal_contrib=False), Author(firstnames='Victress', lastname='Busisiwe Ntsalaze', initials='V', affs=[], is_editor=False, suffix=None, equal_contrib=False), Author(firstnames='Gillian', lastname='Dorse', initials='G', affs=[], is_editor=False, suffix=None, equal_contrib=False), Author(firstnames='Nonzwakazi', lastname='Ntombela', initials='N', affs=[], is_editor=False, suffix=None, equal_contrib=False), Author(firstnames='Cailin', lastname='Ball', initials='C', affs=[], is_editor=False, suffix=None, equal_contrib=False), Author(firstnames='Senzo', lastname='Ndlovu', initials='S', affs=[], is_editor=False, suffix=None, equal_contrib=False), Author(firstnames='Zanele', lastname='Gwamanda', initials='Z', affs=[], is_editor=False, suffix=None, equal_contrib=False), Author(firstnames='Dudu', lastname='Dlamini', initials='D', affs=[], is_editor=False, suffix=None, equal_contrib=False), Author(firstnames='Phindile', lastname='Sing', initials='P', affs=[], is_editor=False, suffix=None, equal_contrib=False), Author(firstnames='Senzo', lastname='Hlathi', initials='S', affs=[], is_editor=False, suffix=None, equal_contrib=False), Author(firstnames='Goodness', lastname='Gumede', initials='G', affs=[], is_editor=False, suffix=None, equal_contrib=False), Author(firstnames='Atika', lastname='Moosa', initials='A', affs=[], is_editor=False, suffix=None, equal_contrib=False), Author(firstnames='Lindiwe', lastname='Ngcobo', initials='L', affs=[], is_editor=False, suffix=None, equal_contrib=False), Author(firstnames='Sindiswa', lastname='Msomi', initials='S', affs=[], is_editor=False, suffix=None, equal_contrib=False), Author(firstnames='Kynesha', lastname='Moopanar', initials='K', affs=[], is_editor=False, suffix=None, equal_contrib=False), Author(firstnames='Kandrelle', lastname='Naidoo', initials='K', affs=[], is_editor=False, suffix=None, equal_contrib=False), Author(firstnames='Elizea', lastname='Horne', initials='E', affs=[], is_editor=False, suffix=None, equal_contrib=False), Author(firstnames='Faeezah', lastname='Patel', initials='F', affs=[], is_editor=False, suffix=None, equal_contrib=False), Author(firstnames='Tiffany', lastname='Seef', initials='T', affs=[], is_editor=False, suffix=None, equal_contrib=False), Author(firstnames='Othusitse', lastname='Segalo', initials='O', affs=[], is_editor=False, suffix=None, equal_contrib=False), Author(firstnames='Jeanne', lastname='Coetzee', initials='J', affs=[], is_editor=False, suffix=None, equal_contrib=False), Author(firstnames='Muneerah', lastname='Khan', initials='M', affs=[], is_editor=False, suffix=None, equal_contrib=False), Author(firstnames='Israel', lastname='Mzizi', initials='I', affs=[], is_editor=False, suffix=None, equal_contrib=False), Author(firstnames='Rorisang', lastname='Komane', initials='R', affs=[], is_editor=False, suffix=None, equal_contrib=False), Author(firstnames='Hamisha', lastname='Soma-Kasiram', initials='H', affs=[], is_editor=False, suffix=None, equal_contrib=False), Author(firstnames='Vimbisai', lastname='Mukoko', initials='V', affs=[], is_editor=False, suffix=None, equal_contrib=False), Author(firstnames='Saajida', lastname='Akhalwaya', initials='S', affs=[], is_editor=False, suffix=None, equal_contrib=False), Author(firstnames='Stela', lastname='Mthombeni', initials='S', affs=[], is_editor=False, suffix=None, equal_contrib=False), Author(firstnames='Thando', lastname='Ntuli', initials='T', affs=[], is_editor=False, suffix=None, equal_contrib=False), Author(firstnames='Mapule', lastname='Moloi', initials='M', affs=[], is_editor=False, suffix=None, equal_contrib=False), Author(firstnames='Sanele', lastname='Nkosi', initials='S', affs=[], is_editor=False, suffix=None, equal_contrib=False), Author(firstnames='Angela', lastname='Oosthuizen', initials='A', affs=[], is_editor=False, suffix=None, equal_contrib=False), Author(firstnames='Janet', lastname='Grab', initials='J', affs=[], is_editor=False, suffix=None, equal_contrib=False), Author(firstnames='Masebole', lastname='Masenya', initials='M', affs=[], is_editor=False, suffix=None, equal_contrib=False)], affs=[]), Adolescent, BCG Vaccine* / adverse effects, BCG Vaccine* / immunology, Child, Double-Blind Method, Female, Humans, Immunization, Secondary*, Intention to Treat Analysis, Interferon-gamma Release Tests, Male, Mycobacterium tuberculosis* / immunology, Tuberculosis* / prevention & control, Vaccine Efficacy*, Young Adult, PubMed Abstract, NIH, NLM, NCBI, National Institutes of Health, National Center for Biotechnology Information, National Library of Medicine, MEDLINE",
        "robots": "index,nofollow,noarchive",
        "og:title": "BCG Revaccination for the Prevention of Mycobacterium tuberculosis Infection - PubMed",
        "og:url": "https://pubmed.ncbi.nlm.nih.gov/40334156/",
        "og:description": "BCG revaccination in QFT-test negative, HIV-negative adolescents did not provide protection from sustained <i>M. tuberculosis</i> infection. (Funded by the Gates Foundation; ClinicalTrials.gov number NCT04152161.).",
        "og:image": "https://cdn.ncbi.nlm.nih.gov/pubmed/persistent/pubmed-meta-image-v2.jpg",
        "og:image:secure_url": "https://cdn.ncbi.nlm.nih.gov/pubmed/persistent/pubmed-meta-image-v2.jpg",
        "og:type": "website",
        "og:site_name": "PubMed",
        "twitter:domain": "pubmed.ncbi.nlm.nih.gov",
        "twitter:card": "summary_large_image",
        "twitter:title": "BCG Revaccination for the Prevention of Mycobacterium tuberculosis Infection - PubMed",
        "twitter:url": "https://pubmed.ncbi.nlm.nih.gov/40334156/",
        "twitter:description": "BCG revaccination in QFT-test negative, HIV-negative adolescents did not provide protection from sustained <i>M. tuberculosis</i> infection. (Funded by the Gates Foundation; ClinicalTrials.gov number NCT04152161.).",
        "twitter:image": "https://cdn.ncbi.nlm.nih.gov/pubmed/persistent/pubmed-meta-image-v2.jpg",
        "citation_title": "BCG Revaccination for the Prevention of Mycobacterium tuberculosis Infection",
        "citation_authors": "Schmidt AC;Fairlie L;Hellstr\u00f6m E;Luabeya Kany Kany A;Middelkoop K;Naidoo K;Nair G;Gela A;Nemes E;Scriba TJ;Cinar A;Frahm N;Mogg R;Kaufman D;Dunne MW;Hatherill M; ;",
        "citation_date": "05/08/2025",
        "citation_publisher": "N Engl J Med",
        "citation_journal_title": "The New England journal of medicine",
        "citation_pmid": "40334156",
        "citation_abstract_html_url": "https://pubmed.ncbi.nlm.nih.gov/40334156/",
        "citation_volume": "392",
        "citation_issue": "18",
        "citation_doi": "10.1056/NEJMoa2412381",
        "citation_issn": "1533-4406",
        "title": "BCG Revaccination for the Prevention of Mycobacterium tuberculosis Infection - PubMed"
      },
      "trafilatura_metadata": {
        "title": "BCG Revaccination for the Prevention of Mycobacterium tuberculosis Infection - PubMed",
        "author": "Username",
        "date": "2025-05-08",
        "keywords": null,
        "description": null,
        "source": "https://pubmed.ncbi.nlm.nih.gov/40334156/"
      }
    }
  ]
}
